{
    "elected": "division/newcastle",
    "first_name": "Sharon",
    "last_name": "GRIERSON",
    "party": "alp",
    "retiring": false,
    "term_start": "2001-11-10",
    "wikipedia": "http://en.wikipedia.org/wiki/Sharon_Grierson",
    "website": "http://www.sharongrierson.com/",
    "parliment_link": "http://www.aph.gov.au/Senators_and_Members/Parliamentarian?MPID=00AMP",
    "open_australia_link": "http://www.openaustralia.org/mp/sharon_grierson",
    "image": "http://www.openaustralia.org/images/mpsL/10266.jpg",
    "entered_reason": "general_election"
}